metasrc/__init__.py
metasrc/_version.py
metasrc/git/__init__.py
metasrc/git/timestamp.py
metasrc/github/__init__.py
metasrc/github/auth.py
metasrc/pandoc/__init__.py
metasrc/pandoc/convert.py
metasrc/pandoc/filters/__init__.py
metasrc/pandoc/filters/deparagraph.py
metasrc/tex/__init__.py
metasrc/tex/citelink.py
metasrc/tex/commandparser.py
metasrc/tex/lsstbib.py
metasrc/tex/lsstdoc.py
metasrc/tex/lsstmacros.py
metasrc/tex/normalizer.py
metasrc/tex/scraper.py
metasrc-0.2.2.dist-info/DESCRIPTION.rst
metasrc-0.2.2.dist-info/METADATA
metasrc-0.2.2.dist-info/RECORD
metasrc-0.2.2.dist-info/WHEEL
metasrc-0.2.2.dist-info/entry_points.txt
metasrc-0.2.2.dist-info/metadata.json
metasrc-0.2.2.dist-info/top_level.txt
